LICENSE
MANIFEST.in
README.md
pyproject.toml
setup.cfg
setup.py
tests/__init__.py
tests/testapp/__init__.py
tests/testapp/manage.py
tests/testapp/core/__init__.py
tests/testapp/core/tests.py
tests/testapp/core/migrations/__init__.py
tests/testapp/testapp/__init__.py
tests/testapp/testapp/asgi.py
tests/testapp/testapp/settings.py
tests/testapp/testapp/urls.py
tests/testapp/testapp/wsgi.py
wagtail_mailer/__init__.py
wagtail_mailer/actions.py
wagtail_mailer/admin.py
wagtail_mailer/apps.py
wagtail_mailer/log.py
wagtail_mailer/mailing.py
wagtail_mailer/tasks.py
wagtail_mailer/wagtail_hooks.py
wagtail_mailer.egg-info/PKG-INFO
wagtail_mailer.egg-info/SOURCES.txt
wagtail_mailer.egg-info/dependency_links.txt
wagtail_mailer.egg-info/requires.txt
wagtail_mailer.egg-info/top_level.txt
wagtail_mailer/locale/de/LC_MESSAGES/django.mo
wagtail_mailer/locale/de/LC_MESSAGES/django.po
wagtail_mailer/locale/en/LC_MESSAGES/django.mo
wagtail_mailer/locale/en/LC_MESSAGES/django.po
wagtail_mailer/locale/fr/LC_MESSAGES/django.mo
wagtail_mailer/locale/fr/LC_MESSAGES/django.po
wagtail_mailer/locale/nl/LC_MESSAGES/django.mo
wagtail_mailer/locale/nl/LC_MESSAGES/django.po
wagtail_mailer/migrations/0001_initial.py
wagtail_mailer/migrations/__init__.py
wagtail_mailer/models/__init__.py
wagtail_mailer/models/error_handler.py
wagtail_mailer/models/mailer.py
wagtail_mailer/models/receivers.py
wagtail_mailer/templates/mailer/bulk_actions/list_items_with_no_access.html
wagtail_mailer/templates/mailer/bulk_actions/test_mail.html
wagtail_mailer/templatetags/__init__.py
wagtail_mailer/templatetags/email_tags.py